CYB600_Lab_One-1.1.data/scripts/current-time
csc_cyb600/__init__.py
csc_cyb600/main.py
CYB600_Lab_One-1.1.dist-info/METADATA
CYB600_Lab_One-1.1.dist-info/WHEEL
CYB600_Lab_One-1.1.dist-info/top_level.txt
CYB600_Lab_One-1.1.dist-info/RECORD
